{
  "storage_version": 1,
  "name": "boitier_alarme",
  "friendly_name": null,
  "comment": null,
  "esphome_version": "2024.2.2",
  "src_version": 1,
  "address": "192.168.1.127",
  "web_port": 80,
  "esp_platform": "ESP8266",
  "build_path": ".\\.esphome\\build/boitier_alarme",
  "firmware_bin_path": ".\\.esphome\\build/boitier_alarme\\.pioenvs\\boitier_alarme\\firmware.bin",
  "loaded_integrations": [
    "api",
    "async_tcp",
    "binary_sensor",
    "captive_portal",
    "esp8266",
    "esphome",
    "gpio",
    "json",
    "md5",
    "mdns",
    "network",
    "ota",
    "preferences",
    "rc522",
    "rc522_spi",
    "socket",
    "spi",
    "switch",
    "template",
    "text",
    "text_sensor",
    "web_server",
    "web_server_base",
    "wifi",
    "wifi_info"
  ],
  "no_mdns": false
}
